simula_repo_review/__init__.py
simula_repo_review/__main__.py
simula_repo_review/checks.py
simula_repo_review/cli.py
simula_repo_review-0.1.0.dist-info/METADATA
simula_repo_review-0.1.0.dist-info/WHEEL
simula_repo_review-0.1.0.dist-info/entry_points.txt
simula_repo_review-0.1.0.dist-info/RECORD
