Metadata-Version: 2.4
Name: simula-repo-review
Version: 0.1.0
Summary: Add your description here
Author-email: Henrik Finsberg <henriknf@simula.no>
Requires-Python: >=3.12.9
Requires-Dist: repo-review[cli]>=0.12.3
Requires-Dist: sp-repo-review[cli]>=2025.10.20
Provides-Extra: test
Requires-Dist: pytest>=8.4.2; extra == 'test'
